pibronic/__init__.py
pibronic/constants.py
pibronic/electronic_structure.py
pibronic/everything.py
pibronic/helper.py
pibronic/julia_wrapper.py
pibronic/log_conf.py
pibronic/data/__init__.py
pibronic/data/file_name.py
pibronic/data/file_structure.py
pibronic/data/postprocessing.py
pibronic/pimc/__init__.py
pibronic/pimc/pimc.py
pibronic/plotting/__init__.py
pibronic/plotting/plotting.py
pibronic/server/__init__.py
pibronic/server/job_boss.py
pibronic/server/pimc.py
pibronic/server/pimc_array_dispatcher.py
pibronic/server/pimc_job_dispatcher.py
pibronic/server/rho_job_dispatcher.py
pibronic/server/server.py
pibronic/server/trotter_job_dispatcher.py
pibronic/stats/__init__.py
pibronic/stats/jackknife.py
pibronic/stats/jackknife_old.py
pibronic/stats/stats.py
pibronic/vibronic/__init__.py
pibronic/vibronic/electronic_structure.py
pibronic/vibronic/model_auto.py
pibronic/vibronic/model_h.py
pibronic/vibronic/model_op.py
pibronic/vibronic/vibronic_model_io.py
pibronic/vibronic/vibronic_model_keys.py
pibronic-0.2.0.dev1.dist-info/METADATA
pibronic-0.2.0.dev1.dist-info/RECORD
pibronic-0.2.0.dev1.dist-info/WHEEL
pibronic-0.2.0.dev1.dist-info/top_level.txt
tests/data/__init__.py
tests/data/test_file_structure.py
tests/data/test_postprocessing.py
tests/pimc/__init__.py
tests/pimc/test_pimc.py
tests/plotting/__init__.py
tests/server/__init__.py
tests/server/test_job_boss.py
tests/server/test_pimc_job_dispatcher.py
tests/server/test_rho_job_dispatcher.py
tests/stats/__init__.py
tests/stats/test_jackknife.py
tests/stats/test_stats.py
tests/vibronic/__init__.py
tests/vibronic/test_electronic_structure.py
tests/vibronic/test_vibronic_model_io.py
