Metadata-Version: 2.1
Name: pibronic
Version: 0.2.0.dev1
Summary: Quantum Mechanical Computational Package
Home-page: https://github.com/ngraymon/pibronic
Author: Neil Raymond
Author-email: neil.raymond@uwaterloo.ca
License: MIT
Keywords: path_integral_monte_carlo quantum_mechanics chemistry vibronic
Platform: UNKNOWN
Classifier: Development Status :: 3 - Alpha
Classifier: Intended Audience :: Science/Research
Classifier: Topic :: Scientific/Engineering :: Chemistry
Classifier: License :: OSI Approved :: MIT License
Classifier: Programming Language :: Python :: 3.6
Classifier: Programming Language :: Python :: 3.7
Requires-Python: ~=3.6
Provides-Extra: dev
Provides-Extra: test
Requires-Dist: numpy (>=1.12)
Requires-Dist: scipy (>=1.0.0)
Requires-Dist: matplotlib (>=2.1.2)
Requires-Dist: fortranformat (==0.2.5)
Requires-Dist: parse (==1.8.2)
Provides-Extra: dev
Requires-Dist: check-manifest; extra == 'dev'
Provides-Extra: test
Requires-Dist: coverage; extra == 'test'
Requires-Dist: pytest; extra == 'test'
